hydro_snap/__init__.py
hydro_snap/hydro_snap.py
hydro_snap-0.1.4.dist-info/LICENSE
hydro_snap-0.1.4.dist-info/METADATA
hydro_snap-0.1.4.dist-info/WHEEL
hydro_snap-0.1.4.dist-info/top_level.txt
hydro_snap-0.1.4.dist-info/RECORD
