Metadata-Version: 2.1
Name: hydro-snap
Version: 0.1.4
Summary: DEM reconditioning for hydrological applications
Author: Pascal Horton
Author-email: pascal.horton@unibe.ch
License: MIT
Project-URL: Source Code, https://github.com/pascalhorton/hydro-snap
Project-URL: Bug Tracker, https://github.com/pascalhorton/hydro-snap/issues
Classifier: Programming Language :: Python
Classifier: Programming Language :: Python :: 3
Classifier: License :: OSI Approved :: MIT License
Requires-Python: >=3.8
License-File: LICENSE
Requires-Dist: fiona
Requires-Dist: geopandas
Requires-Dist: numpy==1.*
Requires-Dist: pysheds
Requires-Dist: rasterio
Requires-Dist: shapely
